avsub/__init__.py
avsub/__main__.py
avsub/cli.py
avsub/ffmpeg.py
avsub/new.py
avsub/registry.py
avsub/str.py
avsub/core/__init__.py
avsub/core/consts.py
avsub/core/errors.py
avsub/core/notice_.py
avsub/core/tools.py
avsub/core/x.py
avsub-2.6.0.dist-info/LICENSE
avsub-2.6.0.dist-info/METADATA
avsub-2.6.0.dist-info/WHEEL
avsub-2.6.0.dist-info/entry_points.txt
avsub-2.6.0.dist-info/top_level.txt
avsub-2.6.0.dist-info/RECORD
