Metadata-Version: 2.1
Name: avsub
Version: 2.6.0
Summary: A simplified command-line interface for FFmpeg
Home-page: https://github.com/serhatcelik/avsub
Download-URL: https://github.com/serhatcelik/avsub/releases/latest
Author: Serhat Çelik
Author-email: prjctsrht@gmail.com
License: GPLv3
Project-URL: Source Code, https://github.com/serhatcelik/avsub
Project-URL: Bug Tracker, https://github.com/serhatcelik/avsub/issues
Project-URL: Documentation, https://github.com/serhatcelik/avsub/wiki
Project-URL: Say Thanks!, https://saythanks.io/to/serhatcelik
Keywords: avsub,audio,video,subtitle,ffmpeg
Platform: Linux
Platform: Windows
Classifier: Development Status :: 5 - Production/Stable
Classifier: Environment :: Console
Classifier: Intended Audience :: End Users/Desktop
Classifier: License :: OSI Approved :: GNU General Public License v3 (GPLv3)
Classifier: Natural Language :: English
Classifier: Operating System :: Microsoft :: Windows
Classifier: Operating System :: Microsoft :: Windows :: Windows 10
Classifier: Operating System :: POSIX
Classifier: Operating System :: POSIX :: Linux
Classifier: Programming Language :: Python :: 3 :: Only
Classifier: Programming Language :: Python :: 3.6
Classifier: Programming Language :: Python :: 3.7
Classifier: Programming Language :: Python :: 3.8
Classifier: Programming Language :: Python :: 3.9
Classifier: Programming Language :: Python :: 3.10
Classifier: Topic :: Multimedia
Classifier: Topic :: Multimedia :: Sound/Audio
Classifier: Topic :: Multimedia :: Sound/Audio :: Conversion
Classifier: Topic :: Multimedia :: Video
Classifier: Topic :: Multimedia :: Video :: Conversion
Requires-Python: ~=3.6
License-File: LICENSE
